<annotation>
	<folder>9-split</folder>
	<filename>1002711.jpg</filename>
	<path>D:\研究生\图片标记\twitter2015\img_split_11\9-split\1002711.jpg</path>
	<source>
		<database>Unknown</database>
	</source>
	<size>
		<width>600</width>
		<height>326</height>
		<depth>3</depth>
	</size>
	<segmented>0</segmented>
	<object>
		<name>Kourtney K</name>
		<pose>Unspecified</pose>
		<truncated>1</truncated>
		<difficult>0</difficult>
		<bndbox>
			<xmin>216</xmin>
			<ymin>7</ymin>
			<xmax>570</xmax>
			<ymax>326</ymax>
		</bndbox>
	</object>
</annotation>
