<annotation>
	<folder>1-split</folder>
	<filename>38139.jpg</filename>
	<path>D:\研究生\图片标记\twitter2015_1114_4\img_split_4\1-split\38139.jpg</path>
	<source>
		<database>Unknown</database>
	</source>
	<size>
		<width>600</width>
		<height>399</height>
		<depth>3</depth>
	</size>
	<segmented>0</segmented>
	<object>
		<name>Derek Jeter</name>
		<pose>Unspecified</pose>
		<truncated>1</truncated>
		<difficult>0</difficult>
		<bndbox>
			<xmin>71</xmin>
			<ymin>196</ymin>
			<xmax>255</xmax>
			<ymax>399</ymax>
		</bndbox>
	</object>
</annotation>
