<annotation>
	<folder>3-split</folder>
	<filename>706391.jpg</filename>
	<path>C:\Users\lenovo\Documents\work\dataset\twitter2015_1114_4\img_split_4\3-split\706391.jpg</path>
	<source>
		<database>Unknown</database>
	</source>
	<size>
		<width>403</width>
		<height>252</height>
		<depth>3</depth>
	</size>
	<segmented>0</segmented>
	<object>
		<name>Robin van Persie</name>
		<pose>Unspecified</pose>
		<truncated>1</truncated>
		<difficult>0</difficult>
		<bndbox>
			<xmin>60</xmin>
			<ymin>18</ymin>
			<xmax>297</xmax>
			<ymax>252</ymax>
		</bndbox>
	</object>
</annotation>
