<annotation>
	<folder>8-split</folder>
	<filename>884794.jpg</filename>
	<path>D:\研究生\图片标记\twitter2015\img_split_11\8-split\884794.jpg</path>
	<source>
		<database>Unknown</database>
	</source>
	<size>
		<width>600</width>
		<height>761</height>
		<depth>3</depth>
	</size>
	<segmented>0</segmented>
	<object>
		<name>J . Cole</name>
		<pose>Unspecified</pose>
		<truncated>1</truncated>
		<difficult>0</difficult>
		<bndbox>
			<xmin>2</xmin>
			<ymin>155</ymin>
			<xmax>600</xmax>
			<ymax>761</ymax>
		</bndbox>
	</object>
</annotation>
