<annotation>
	<folder>dev</folder>
	<filename>16_05_30_851_region.jpg</filename>
	<path>D:\PyCharm\BERT_NER\data\images\twitter2017_region\dev\16_05_30_851_region.jpg</path>
	<source>
		<database>Unknown</database>
	</source>
	<size>
		<width>780</width>
		<height>1200</height>
		<depth>3</depth>
	</size>
	<segmented>0</segmented>
	<object>
		<name>MC24H ART FESTIVAL</name>
		<pose>Unspecified</pose>
		<truncated>0</truncated>
		<difficult>0</difficult>
		<bndbox>
			<xmin>47</xmin>
			<ymin>286</ymin>
			<xmax>714</xmax>
			<ymax>490</ymax>
		</bndbox>
	</object>
</annotation>
