<annotation>
	<folder>11-split</folder>
	<filename>1870402.jpg</filename>
	<path>D:\研究生\图片标记\twitter2015\img_split_11\11-split\1870402.jpg</path>
	<source>
		<database>Unknown</database>
	</source>
	<size>
		<width>600</width>
		<height>403</height>
		<depth>3</depth>
	</size>
	<segmented>0</segmented>
	<object>
		<name>President Reagan</name>
		<pose>Unspecified</pose>
		<truncated>1</truncated>
		<difficult>0</difficult>
		<bndbox>
			<xmin>29</xmin>
			<ymin>92</ymin>
			<xmax>298</xmax>
			<ymax>403</ymax>
		</bndbox>
	</object>
</annotation>
