<annotation>
	<folder>6-split</folder>
	<filename>417986.jpg</filename>
	<path>D:\研究生\图片标记\twitter2015\img_split_11\6-split\417986.jpg</path>
	<source>
		<database>Unknown</database>
	</source>
	<size>
		<width>600</width>
		<height>450</height>
		<depth>3</depth>
	</size>
	<segmented>0</segmented>
	<object>
		<name>Angie Henry</name>
		<pose>Unspecified</pose>
		<truncated>0</truncated>
		<difficult>0</difficult>
		<bndbox>
			<xmin>190</xmin>
			<ymin>20</ymin>
			<xmax>451</xmax>
			<ymax>347</ymax>
		</bndbox>
	</object>
</annotation>
