<annotation>
	<folder>8-split</folder>
	<filename>670554.jpg</filename>
	<path>D:\研究生\图片标记\twitter2015\img_split_11\8-split\670554.jpg</path>
	<source>
		<database>Unknown</database>
	</source>
	<size>
		<width>592</width>
		<height>596</height>
		<depth>3</depth>
	</size>
	<segmented>0</segmented>
	<object>
		<name>Kanye</name>
		<pose>Unspecified</pose>
		<truncated>0</truncated>
		<difficult>0</difficult>
		<bndbox>
			<xmin>14</xmin>
			<ymin>34</ymin>
			<xmax>74</xmax>
			<ymax>126</ymax>
		</bndbox>
	</object>
	<object>
		<name>Kanye</name>
		<pose>Unspecified</pose>
		<truncated>0</truncated>
		<difficult>0</difficult>
		<bndbox>
			<xmin>199</xmin>
			<ymin>69</ymin>
			<xmax>280</xmax>
			<ymax>148</ymax>
		</bndbox>
	</object>
	<object>
		<name>Kanye</name>
		<pose>Unspecified</pose>
		<truncated>0</truncated>
		<difficult>0</difficult>
		<bndbox>
			<xmin>66</xmin>
			<ymin>272</ymin>
			<xmax>124</xmax>
			<ymax>361</ymax>
		</bndbox>
	</object>
	<object>
		<name>Kanye</name>
		<pose>Unspecified</pose>
		<truncated>0</truncated>
		<difficult>0</difficult>
		<bndbox>
			<xmin>491</xmin>
			<ymin>17</ymin>
			<xmax>581</xmax>
			<ymax>113</ymax>
		</bndbox>
	</object>
	<object>
		<name>Kanye</name>
		<pose>Unspecified</pose>
		<truncated>0</truncated>
		<difficult>0</difficult>
		<bndbox>
			<xmin>95</xmin>
			<ymin>431</ymin>
			<xmax>175</xmax>
			<ymax>525</ymax>
		</bndbox>
	</object>
	<object>
		<name>Kanye</name>
		<pose>Unspecified</pose>
		<truncated>0</truncated>
		<difficult>0</difficult>
		<bndbox>
			<xmin>326</xmin>
			<ymin>219</ymin>
			<xmax>380</xmax>
			<ymax>302</ymax>
		</bndbox>
	</object>
	<object>
		<name>Kanye</name>
		<pose>Unspecified</pose>
		<truncated>0</truncated>
		<difficult>0</difficult>
		<bndbox>
			<xmin>312</xmin>
			<ymin>438</ymin>
			<xmax>394</xmax>
			<ymax>524</ymax>
		</bndbox>
	</object>
	<object>
		<name>Kanye</name>
		<pose>Unspecified</pose>
		<truncated>0</truncated>
		<difficult>0</difficult>
		<bndbox>
			<xmin>414</xmin>
			<ymin>217</ymin>
			<xmax>467</xmax>
			<ymax>302</ymax>
		</bndbox>
	</object>
	<object>
		<name>Kanye</name>
		<pose>Unspecified</pose>
		<truncated>0</truncated>
		<difficult>0</difficult>
		<bndbox>
			<xmin>477</xmin>
			<ymin>439</ymin>
			<xmax>561</xmax>
			<ymax>528</ymax>
		</bndbox>
	</object>
</annotation>
