<annotation>
	<folder>8-split</folder>
	<filename>670986.jpg</filename>
	<path>D:\研究生\图片标记\twitter2015\img_split_11\8-split\670986.jpg</path>
	<source>
		<database>Unknown</database>
	</source>
	<size>
		<width>600</width>
		<height>800</height>
		<depth>3</depth>
	</size>
	<segmented>0</segmented>
	<object>
		<name>Mike Serbinis</name>
		<pose>Unspecified</pose>
		<truncated>0</truncated>
		<difficult>0</difficult>
		<bndbox>
			<xmin>276</xmin>
			<ymin>112</ymin>
			<xmax>507</xmax>
			<ymax>769</ymax>
		</bndbox>
	</object>
	<object>
		<name>Ken Nickerson</name>
		<pose>Unspecified</pose>
		<truncated>0</truncated>
		<difficult>0</difficult>
		<bndbox>
			<xmin>104</xmin>
			<ymin>148</ymin>
			<xmax>306</xmax>
			<ymax>675</ymax>
		</bndbox>
	</object>
</annotation>
