<annotation>
	<folder>8-split</folder>
	<filename>806488.jpg</filename>
	<path>D:\研究生\图片标记\twitter2015\img_split_11\8-split\806488.jpg</path>
	<source>
		<database>Unknown</database>
	</source>
	<size>
		<width>600</width>
		<height>572</height>
		<depth>3</depth>
	</size>
	<segmented>0</segmented>
	<object>
		<name>Tom DiNapoli</name>
		<pose>Unspecified</pose>
		<truncated>0</truncated>
		<difficult>0</difficult>
		<bndbox>
			<xmin>259</xmin>
			<ymin>217</ymin>
			<xmax>474</xmax>
			<ymax>451</ymax>
		</bndbox>
	</object>
</annotation>
