<annotation>
	<folder>dev</folder>
	<filename>O_3503_region.jpg</filename>
	<path>D:\PyCharm\BERT_NER\data\images\twitter2017_region\dev\O_3503_region.jpg</path>
	<source>
		<database>Unknown</database>
	</source>
	<size>
		<width>400</width>
		<height>400</height>
		<depth>3</depth>
	</size>
	<segmented>0</segmented>
	<object>
		<name>Emma Watson</name>
		<pose>Unspecified</pose>
		<truncated>0</truncated>
		<difficult>0</difficult>
		<bndbox>
			<xmin>25</xmin>
			<ymin>25</ymin>
			<xmax>168</xmax>
			<ymax>398</ymax>
		</bndbox>
	</object>
</annotation>
